[
  {
    "sourceData": {
      "back_required": false,
      "common_name": null,
      "country": "Andorra",
      "country_alpha2": "AD",
      "country_alpha3": "AND",
      "document_type": "REP",
      "has_nfc": false,
      "id": 10045,
      "municipality": null,
      "region_iso": null,
      "region_name": null,
      "tier": null,
      "usecases": [
        "verify"
      ],
      "version": "2018"
    }
  },
  {
    "sourceData": {
      "back_required": true,
      "common_name": null,
      "country": "Austria | Österreich",
      "country_alpha2": "AT",
      "country_alpha3": "AUT",
      "document_type": "REP",
      "has_nfc": false,
      "id": 2986,
      "municipality": null,
      "region_iso": null,
      "region_name": null,
      "tier": null,
      "usecases": [
        "verify"
      ],
      "version": "2009"
    }
  },
  {
    "sourceData": {
      "back_required": true,
      "common_name": null,
      "country": "Austria | Österreich",
      "country_alpha2": "AT",
      "country_alpha3": "AUT",
      "document_type": "REP",
      "has_nfc": true,
      "id": 2987,
      "municipality": null,
      "region_iso": null,
      "region_name": null,
      "tier": null,
      "usecases": [
        "verify"
      ],
      "version": "2014"
    }
  },
  {
    "sourceData": {
      "back_required": true,
      "common_name": null,
      "country": "Austria | Österreich",
      "country_alpha2": "AT",
      "country_alpha3": "AUT",
      "document_type": "REP",
      "has_nfc": true,
      "id": 6005,
      "municipality": null,
      "region_iso": null,
      "region_name": null,
      "tier": null,
      "usecases": [
        "verify"
      ],
      "version": "2011"
    }
  },
  {
    "sourceData": {
      "back_required": true,
      "common_name": null,
      "country": "Austria | Österreich",
      "country_alpha2": "AT",
      "country_alpha3": "AUT",
      "document_type": "REP",
      "has_nfc": false,
      "id": 6006,
      "municipality": null,
      "region_iso": null,
      "region_name": null,
      "tier": null,
      "usecases": [
        "verify"
      ],
      "version": "2012"
    }
  },
  {
    "sourceData": {
      "back_required": false,
      "common_name": null,
      "country": "Austria | Österreich",
      "country_alpha2": "AT",
      "country_alpha3": "AUT",
      "document_type": "REP",
      "has_nfc": false,
      "id": 7647,
      "municipality": null,
      "region_iso": null,
      "region_name": null,
      "tier": null,
      "usecases": [
        "verify"
      ],
      "version": "2008"
    }
  },
  {
    "sourceData": {
      "back_required": true,
      "common_name": null,
      "country": "Austria | Österreich",
      "country_alpha2": "AT",
      "country_alpha3": "AUT",
      "document_type": "REP",
      "has_nfc": true,
      "id": 9197,
      "municipality": null,
      "region_iso": null,
      "region_name": null,
      "tier": "tier1",
      "usecases": [
        "verify"
      ],
      "version": "2020"
    }
  },
  {
    "sourceData": {
      "back_required": true,
      "common_name": null,
      "country": "Belgium | België",
      "country_alpha2": "BE",
      "country_alpha3": "BEL",
      "document_type": "REP",
      "has_nfc": false,
      "id": 3037,
      "municipality": null,
      "region_iso": null,
      "region_name": null,
      "tier": null,
      "usecases": [
        "verify"
      ],
      "version": "2013"
    }
  },
  {
    "sourceData": {
      "back_required": true,
      "common_name": null,
      "country": "Belgium | België",
      "country_alpha2": "BE",
      "country_alpha3": "BEL",
      "document_type": "REP",
      "has_nfc": false,
      "id": 4587,
      "municipality": null,
      "region_iso": null,
      "region_name": null,
      "tier": null,
      "usecases": [
        "verify"
      ],
      "version": "2015"
    }
  },
  {
    "sourceData": {
      "back_required": true,
      "common_name": null,
      "country": "Belgium | België",
      "country_alpha2": "BE",
      "country_alpha3": "BEL",
      "document_type": "REP",
      "has_nfc": false,
      "id": 4638,
      "municipality": null,
      "region_iso": "WAL",
      "region_name": "Wallonia",
      "tier": null,
      "usecases": [
        "verify"
      ],
      "version": "2015"
    }
  },
  {
    "sourceData": {
      "back_required": true,
      "common_name": null,
      "country": "Belgium | België",
      "country_alpha2": "BE",
      "country_alpha3": "BEL",
      "document_type": "REP",
      "has_nfc": false,
      "id": 4640,
      "municipality": null,
      "region_iso": "WAL",
      "region_name": "Wallonia",
      "tier": null,
      "usecases": [
        "verify"
      ],
      "version": "2013"
    }
  },
  {
    "sourceData": {
      "back_required": true,
      "common_name": null,
      "country": "Belgium | België",
      "country_alpha2": "BE",
      "country_alpha3": "BEL",
      "document_type": "REP",
      "has_nfc": false,
      "id": 4641,
      "municipality": null,
      "region_iso": null,
      "region_name": null,
      "tier": null,
      "usecases": [
        "verify"
      ],
      "version": "2013"
    }
  },
  {
    "sourceData": {
      "back_required": false,
      "common_name": null,
      "country": "Belgium | België",
      "country_alpha2": "BE",
      "country_alpha3": "BEL",
      "document_type": "REP",
      "has_nfc": false,
      "id": 6011,
      "municipality": null,
      "region_iso": "VLG",
      "region_name": "Flanders",
      "tier": null,
      "usecases": [
        "verify"
      ],
      "version": "2008"
    }
  },
  {
    "sourceData": {
      "back_required": false,
      "common_name": null,
      "country": "Belgium | België",
      "country_alpha2": "BE",
      "country_alpha3": "BEL",
      "document_type": "REP",
      "has_nfc": false,
      "id": 6012,
      "municipality": null,
      "region_iso": "WAL",
      "region_name": "Wallonia",
      "tier": null,
      "usecases": [
        "verify"
      ],
      "version": "2008"
    }
  },
  {
    "sourceData": {
      "back_required": true,
      "common_name": null,
      "country": "Belgium | België",
      "country_alpha2": "BE",
      "country_alpha3": "BEL",
      "document_type": "REP",
      "has_nfc": false,
      "id": 6016,
      "municipality": null,
      "region_iso": "VLG",
      "region_name": "Flanders",
      "tier": null,
      "usecases": [
        "verify"
      ],
      "version": "2007"
    }
  },
  {
    "sourceData": {
      "back_required": true,
      "common_name": null,
      "country": "Belgium | België",
      "country_alpha2": "BE",
      "country_alpha3": "BEL",
      "document_type": "REP",
      "has_nfc": false,
      "id": 6017,
      "municipality": null,
      "region_iso": "WAL",
      "region_name": "Wallonia",
      "tier": null,
      "usecases": [
        "verify"
      ],
      "version": "2007"
    }
  },
  {
    "sourceData": {
      "back_required": true,
      "common_name": null,
      "country": "Belgium | België",
      "country_alpha2": "BE",
      "country_alpha3": "BEL",
      "document_type": "REP",
      "has_nfc": false,
      "id": 6019,
      "municipality": null,
      "region_iso": "VLG",
      "region_name": "Flanders",
      "tier": null,
      "usecases": [
        "verify"
      ],
      "version": "2006"
    }
  },
  {
    "sourceData": {
      "back_required": true,
      "common_name": null,
      "country": "Belgium | België",
      "country_alpha2": "BE",
      "country_alpha3": "BEL",
      "document_type": "REP",
      "has_nfc": false,
      "id": 6020,
      "municipality": null,
      "region_iso": "WAL",
      "region_name": "Wallonia",
      "tier": null,
      "usecases": [
        "verify"
      ],
      "version": "2006"
    }
  },
  {
    "sourceData": {
      "back_required": true,
      "common_name": "",
      "country": "Belgium | België",
      "country_alpha2": "BE",
      "country_alpha3": "BEL",
      "document_type": "REP",
      "has_nfc": false,
      "id": 6021,
      "municipality": null,
      "region_iso": null,
      "region_name": null,
      "tier": null,
      "usecases": [
        "verify"
      ],
      "version": "2006"
    }
  },
  {
    "sourceData": {
      "back_required": true,
      "common_name": null,
      "country": "Belgium | België",
      "country_alpha2": "BE",
      "country_alpha3": "BEL",
      "document_type": "REP",
      "has_nfc": true,
      "id": 10265,
      "municipality": null,
      "region_iso": null,
      "region_name": null,
      "tier": "tier1",
      "usecases": [
        "verify"
      ],
      "version": "2021"
    }
  },
  {
    "sourceData": {
      "back_required": true,
      "common_name": null,
      "country": "Belgium | België",
      "country_alpha2": "BE",
      "country_alpha3": "BEL",
      "document_type": "REP",
      "has_nfc": true,
      "id": 10378,
      "municipality": null,
      "region_iso": null,
      "region_name": null,
      "tier": "tier1",
      "usecases": [
        "verify"
      ],
      "version": "2020"
    }
  },
  {
    "sourceData": {
      "back_required": true,
      "common_name": null,
      "country": "Belgium | België",
      "country_alpha2": "BE",
      "country_alpha3": "BEL",
      "document_type": "REP",
      "has_nfc": true,
      "id": 10386,
      "municipality": "Heist-Op",
      "region_iso": "VAN",
      "region_name": "Antwerpen (nl)",
      "tier": "tier1",
      "usecases": [
        "verify"
      ],
      "version": "2020"
    }
  },
  {
    "sourceData": {
      "back_required": true,
      "common_name": null,
      "country": "Belgium | België",
      "country_alpha2": "BE",
      "country_alpha3": "BEL",
      "document_type": "REP",
      "has_nfc": true,
      "id": 6014,
      "municipality": null,
      "region_iso": "VLG",
      "region_name": "Flanders",
      "tier": null,
      "usecases": [
        "verify"
      ],
      "version": "2013"
    }
  },
  {
    "sourceData": {
      "back_required": true,
      "common_name": null,
      "country": "Belgium | België",
      "country_alpha2": "BE",
      "country_alpha3": "BEL",
      "document_type": "REP",
      "has_nfc": false,
      "id": 10423,
      "municipality": null,
      "region_iso": null,
      "region_name": null,
      "tier": "tier1",
      "usecases": [
        "verify"
      ],
      "version": "2021 2"
    }
  },
  {
    "sourceData": {
      "back_required": true,
      "common_name": null,
      "country": "Brazil | Brasil",
      "country_alpha2": "BR",
      "country_alpha3": "BRA",
      "document_type": "REP",
      "has_nfc": false,
      "id": 10064,
      "municipality": null,
      "region_iso": null,
      "region_name": null,
      "tier": "tier3",
      "usecases": [
        "verify"
      ],
      "version": "2013"
    }
  },
  {
    "sourceData": {
      "back_required": true,
      "common_name": null,
      "country": "Brazil | Brasil",
      "country_alpha2": "BR",
      "country_alpha3": "BRA",
      "document_type": "REP",
      "has_nfc": false,
      "id": 10084,
      "municipality": null,
      "region_iso": null,
      "region_name": null,
      "tier": "tier2",
      "usecases": [
        "verify"
      ],
      "version": "1"
    }
  },
  {
    "sourceData": {
      "back_required": true,
      "common_name": null,
      "country": "Bulgaria | България",
      "country_alpha2": "BG",
      "country_alpha3": "BGR",
      "document_type": "REP",
      "has_nfc": true,
      "id": 3098,
      "municipality": null,
      "region_iso": null,
      "region_name": null,
      "tier": null,
      "usecases": [
        "verify"
      ],
      "version": "2009"
    }
  },
  {
    "sourceData": {
      "back_required": true,
      "common_name": null,
      "country": "Bulgaria | България",
      "country_alpha2": "BG",
      "country_alpha3": "BGR",
      "document_type": "REP",
      "has_nfc": false,
      "id": 3099,
      "municipality": null,
      "region_iso": null,
      "region_name": null,
      "tier": null,
      "usecases": [
        "verify"
      ],
      "version": "2008"
    }
  },
  {
    "sourceData": {
      "back_required": true,
      "common_name": null,
      "country": "Bulgaria | България",
      "country_alpha2": "BG",
      "country_alpha3": "BGR",
      "document_type": "REP",
      "has_nfc": false,
      "id": 10039,
      "municipality": null,
      "region_iso": null,
      "region_name": null,
      "tier": "tier1",
      "usecases": [
        "verify"
      ],
      "version": "2010a"
    }
  },
  {
    "sourceData": {
      "back_required": true,
      "common_name": null,
      "country": "Bulgaria | България",
      "country_alpha2": "BG",
      "country_alpha3": "BGR",
      "document_type": "REP",
      "has_nfc": false,
      "id": 10540,
      "municipality": null,
      "region_iso": null,
      "region_name": null,
      "tier": "tier1",
      "usecases": [
        "verify"
      ],
      "version": "2010b"
    }
  },
  {
    "sourceData": {
      "back_required": true,
      "common_name": null,
      "country": "Bulgaria | България",
      "country_alpha2": "BG",
      "country_alpha3": "BGR",
      "document_type": "REP",
      "has_nfc": false,
      "id": 10541,
      "municipality": null,
      "region_iso": null,
      "region_name": null,
      "tier": "tier1",
      "usecases": [
        "verify"
      ],
      "version": "2010"
    }
  },
  {
    "sourceData": {
      "back_required": true,
      "common_name": null,
      "country": "Bulgaria | България",
      "country_alpha2": "BG",
      "country_alpha3": "BGR",
      "document_type": "REP",
      "has_nfc": false,
      "id": 10542,
      "municipality": null,
      "region_iso": null,
      "region_name": null,
      "tier": "tier1",
      "usecases": [
        "verify"
      ],
      "version": "2010"
    }
  },
  {
    "sourceData": {
      "back_required": true,
      "common_name": null,
      "country": "Canada",
      "country_alpha2": "CA",
      "country_alpha3": "CAN",
      "document_type": "REP",
      "has_nfc": false,
      "id": 5193,
      "municipality": null,
      "region_iso": null,
      "region_name": null,
      "tier": null,
      "usecases": [
        "verify"
      ],
      "version": "2015"
    }
  },
  {
    "sourceData": {
      "back_required": true,
      "common_name": null,
      "country": "Canada",
      "country_alpha2": "CA",
      "country_alpha3": "CAN",
      "document_type": "REP",
      "has_nfc": false,
      "id": 5535,
      "municipality": null,
      "region_iso": null,
      "region_name": null,
      "tier": null,
      "usecases": [
        "verify"
      ],
      "version": "2009"
    }
  },
  {
    "sourceData": {
      "back_required": false,
      "common_name": null,
      "country": "China | 中国",
      "country_alpha2": "CN",
      "country_alpha3": "CHN",
      "document_type": "REP",
      "has_nfc": false,
      "id": 9840,
      "municipality": null,
      "region_iso": null,
      "region_name": null,
      "tier": null,
      "usecases": [
        "verify"
      ],
      "version": "2019"
    }
  },
  {
    "sourceData": {
      "back_required": true,
      "common_name": "Cedula de Extrajeria",
      "country": "Colombia",
      "country_alpha2": "CO",
      "country_alpha3": "COL",
      "document_type": "REP",
      "has_nfc": false,
      "id": 5437,
      "municipality": null,
      "region_iso": null,
      "region_name": null,
      "tier": "tier1",
      "usecases": [
        "verify"
      ],
      "version": "2014"
    }
  },
  {
    "sourceData": {
      "back_required": false,
      "common_name": null,
      "country": "Congo",
      "country_alpha2": "CG",
      "country_alpha3": "COG",
      "document_type": "REP",
      "has_nfc": false,
      "id": 9885,
      "municipality": null,
      "region_iso": null,
      "region_name": null,
      "tier": null,
      "usecases": [
        "verify"
      ],
      "version": null
    }
  },
  {
    "sourceData": {
      "back_required": true,
      "common_name": null,
      "country": "Costa Rica",
      "country_alpha2": "CR",
      "country_alpha3": "CRI",
      "document_type": "REP",
      "has_nfc": false,
      "id": 5072,
      "municipality": null,
      "region_iso": null,
      "region_name": null,
      "tier": null,
      "usecases": [
        "verify"
      ],
      "version": "2009"
    }
  },
  {
    "sourceData": {
      "back_required": true,
      "common_name": null,
      "country": "Croatia | Hrvatska",
      "country_alpha2": "HR",
      "country_alpha3": "HRV",
      "document_type": "REP",
      "has_nfc": true,
      "id": 3189,
      "municipality": null,
      "region_iso": null,
      "region_name": null,
      "tier": null,
      "usecases": [
        "verify"
      ],
      "version": "2013"
    }
  },
  {
    "sourceData": {
      "back_required": true,
      "common_name": null,
      "country": "Croatia | Hrvatska",
      "country_alpha2": "HR",
      "country_alpha3": "HRV",
      "document_type": "REP",
      "has_nfc": false,
      "id": 10396,
      "municipality": null,
      "region_iso": null,
      "region_name": null,
      "tier": "tier1",
      "usecases": [
        "verify"
      ],
      "version": "2021"
    }
  },
  {
    "sourceData": {
      "back_required": true,
      "common_name": null,
      "country": "Cyprus | Κύπρος",
      "country_alpha2": "CY",
      "country_alpha3": "CYP",
      "document_type": "REP",
      "has_nfc": true,
      "id": 5123,
      "municipality": null,
      "region_iso": null,
      "region_name": null,
      "tier": null,
      "usecases": [
        "verify"
      ],
      "version": "2014"
    }
  },
  {
    "sourceData": {
      "back_required": false,
      "common_name": null,
      "country": "Cyprus | Κύπρος",
      "country_alpha2": "CY",
      "country_alpha3": "CYP",
      "document_type": "REP",
      "has_nfc": true,
      "id": 9131,
      "municipality": null,
      "region_iso": null,
      "region_name": null,
      "tier": "tier1",
      "usecases": [
        "verify"
      ],
      "version": "2020"
    }
  },
  {
    "sourceData": {
      "back_required": true,
      "common_name": null,
      "country": "Czech Republic | Česko",
      "country_alpha2": "CZ",
      "country_alpha3": "CZE",
      "document_type": "REP",
      "id": 4844,
      "region_iso": null,
      "usecases": [
        "verify"
      ],
      "version": "2014"
    }
  },
  {
    "sourceData": {
      "back_required": true,
      "common_name": null,
      "country": "Czech Republic | Česko",
      "country_alpha2": "CZ",
      "country_alpha3": "CZE",
      "document_type": "REP",
      "has_nfc": true,
      "id": 3224,
      "municipality": null,
      "region_iso": null,
      "region_name": null,
      "tier": null,
      "usecases": [
        "verify"
      ],
      "version": "2015"
    }
  },
  {
    "sourceData": {
      "back_required": true,
      "common_name": null,
      "country": "Czech Republic | Česko",
      "country_alpha2": "CZ",
      "country_alpha3": "CZE",
      "document_type": "REP",
      "has_nfc": true,
      "id": 4843,
      "municipality": null,
      "region_iso": null,
      "region_name": null,
      "tier": null,
      "usecases": [
        "verify"
      ],
      "version": "2011"
    }
  },
  {
    "sourceData": {
      "back_required": false,
      "common_name": null,
      "country": "Czech Republic | Česko",
      "country_alpha2": "CZ",
      "country_alpha3": "CZE",
      "document_type": "REP",
      "has_nfc": false,
      "id": 4847,
      "municipality": null,
      "region_iso": null,
      "region_name": null,
      "tier": null,
      "usecases": [
        "verify"
      ],
      "version": "2013"
    }
  },
  {
    "sourceData": {
      "back_required": true,
      "common_name": null,
      "country": "Czech Republic | Česko",
      "country_alpha2": "CZ",
      "country_alpha3": "CZE",
      "document_type": "REP",
      "has_nfc": true,
      "id": 9230,
      "municipality": null,
      "region_iso": null,
      "region_name": null,
      "tier": "tier1",
      "usecases": [
        "verify"
      ],
      "version": "2020"
    }
  },
  {
    "sourceData": {
      "back_required": false,
      "common_name": null,
      "country": "Denmark | Danmark",
      "country_alpha2": "DK",
      "country_alpha3": "DNK",
      "document_type": "REP",
      "id": 3239,
      "region_iso": null,
      "usecases": [
        "verify"
      ],
      "version": null
    }
  },
  {
    "sourceData": {
      "back_required": true,
      "common_name": null,
      "country": "Denmark | Danmark",
      "country_alpha2": "DK",
      "country_alpha3": "DNK",
      "document_type": "REP",
      "has_nfc": true,
      "id": 3238,
      "municipality": null,
      "region_iso": null,
      "region_name": null,
      "tier": null,
      "usecases": [
        "verify"
      ],
      "version": "2012 1"
    }
  },
  {
    "sourceData": {
      "back_required": true,
      "common_name": null,
      "country": "Denmark | Danmark",
      "country_alpha2": "DK",
      "country_alpha3": "DNK",
      "document_type": "REP",
      "has_nfc": false,
      "id": 6037,
      "municipality": null,
      "region_iso": null,
      "region_name": null,
      "tier": null,
      "usecases": [
        "verify"
      ],
      "version": "2003"
    }
  },
  {
    "sourceData": {
      "back_required": false,
      "common_name": null,
      "country": "Denmark | Danmark",
      "country_alpha2": "DK",
      "country_alpha3": "DNK",
      "document_type": "REP",
      "has_nfc": true,
      "id": 8735,
      "municipality": null,
      "region_iso": null,
      "region_name": null,
      "tier": null,
      "usecases": [
        "verify"
      ],
      "version": "2012 2"
    }
  },
  {
    "sourceData": {
      "back_required": true,
      "common_name": null,
      "country": "Denmark | Danmark",
      "country_alpha2": "DK",
      "country_alpha3": "DNK",
      "document_type": "REP",
      "has_nfc": false,
      "id": 10402,
      "municipality": null,
      "region_iso": null,
      "region_name": null,
      "tier": "tier1",
      "usecases": [
        "verify"
      ],
      "version": "2017_1"
    }
  },
  {
    "sourceData": {
      "back_required": true,
      "common_name": null,
      "country": "Denmark | Danmark",
      "country_alpha2": "DK",
      "country_alpha3": "DNK",
      "document_type": "REP",
      "has_nfc": false,
      "id": 10403,
      "municipality": null,
      "region_iso": null,
      "region_name": null,
      "tier": "tier1",
      "usecases": [
        "verify"
      ],
      "version": "2017_2"
    }
  },
  {
    "sourceData": {
      "back_required": true,
      "common_name": null,
      "country": "Estonia | Eesti",
      "country_alpha2": "EE",
      "country_alpha3": "EST",
      "document_type": "REP",
      "has_nfc": true,
      "id": 3276,
      "municipality": null,
      "region_iso": null,
      "region_name": null,
      "tier": null,
      "usecases": [
        "verify"
      ],
      "version": "2011"
    }
  },
  {
    "sourceData": {
      "back_required": true,
      "common_name": null,
      "country": "Estonia | Eesti",
      "country_alpha2": "EE",
      "country_alpha3": "EST",
      "document_type": "REP",
      "has_nfc": true,
      "id": 4853,
      "municipality": null,
      "region_iso": null,
      "region_name": null,
      "tier": null,
      "usecases": [
        "verify"
      ],
      "version": "2018"
    }
  },
  {
    "sourceData": {
      "back_required": true,
      "common_name": null,
      "country": "Estonia | Eesti",
      "country_alpha2": "EE",
      "country_alpha3": "EST",
      "document_type": "REP",
      "has_nfc": true,
      "id": 4854,
      "municipality": null,
      "region_iso": null,
      "region_name": null,
      "tier": null,
      "usecases": [
        "verify"
      ],
      "version": "2014"
    }
  },
  {
    "sourceData": {
      "back_required": true,
      "common_name": null,
      "country": "Estonia | Eesti",
      "country_alpha2": "EE",
      "country_alpha3": "EST",
      "document_type": "REP",
      "has_nfc": false,
      "id": 4855,
      "municipality": null,
      "region_iso": null,
      "region_name": null,
      "tier": null,
      "usecases": [
        "verify"
      ],
      "version": "2007"
    }
  },
  {
    "sourceData": {
      "back_required": true,
      "common_name": null,
      "country": "Estonia | Eesti",
      "country_alpha2": "EE",
      "country_alpha3": "EST",
      "document_type": "REP",
      "has_nfc": true,
      "id": 4857,
      "municipality": null,
      "region_iso": null,
      "region_name": null,
      "tier": null,
      "usecases": [
        "verify"
      ],
      "version": "2018"
    }
  },
  {
    "sourceData": {
      "back_required": false,
      "common_name": null,
      "country": "Estonia | Eesti",
      "country_alpha2": "EE",
      "country_alpha3": "EST",
      "document_type": "REP",
      "has_nfc": true,
      "id": 9494,
      "municipality": null,
      "region_iso": null,
      "region_name": null,
      "tier": null,
      "usecases": [
        "verify"
      ],
      "version": "2020"
    }
  },
  {
    "sourceData": {
      "back_required": false,
      "common_name": null,
      "country": "Ethiopia | ኢትዮጵያ",
      "country_alpha2": "ET",
      "country_alpha3": "ETH",
      "document_type": "REP",
      "has_nfc": false,
      "id": 4994,
      "municipality": null,
      "region_iso": null,
      "region_name": null,
      "tier": null,
      "usecases": [
        "verify"
      ],
      "version": "2004"
    }
  },
  {
    "sourceData": {
      "back_required": false,
      "common_name": null,
      "country": "Ethiopia | ኢትዮጵያ",
      "country_alpha2": "ET",
      "country_alpha3": "ETH",
      "document_type": "REP",
      "has_nfc": false,
      "id": 5479,
      "municipality": null,
      "region_iso": null,
      "region_name": null,
      "tier": null,
      "usecases": [
        "verify"
      ],
      "version": "2004"
    }
  },
  {
    "sourceData": {
      "back_required": true,
      "common_name": null,
      "country": "Finland | Suomi",
      "country_alpha2": "FI",
      "country_alpha3": "FIN",
      "document_type": "REP",
      "has_nfc": true,
      "id": 5125,
      "municipality": null,
      "region_iso": null,
      "region_name": null,
      "tier": null,
      "usecases": [
        "verify"
      ],
      "version": "2012"
    }
  },
  {
    "sourceData": {
      "back_required": true,
      "common_name": null,
      "country": "Finland | Suomi",
      "country_alpha2": "FI",
      "country_alpha3": "FIN",
      "document_type": "REP",
      "has_nfc": false,
      "id": 6044,
      "municipality": null,
      "region_iso": null,
      "region_name": null,
      "tier": null,
      "usecases": [
        "verify"
      ],
      "version": "2017"
    }
  },
  {
    "sourceData": {
      "back_required": true,
      "common_name": null,
      "country": "Finland | Suomi",
      "country_alpha2": "FI",
      "country_alpha3": "FIN",
      "document_type": "REP",
      "has_nfc": false,
      "id": 6045,
      "municipality": null,
      "region_iso": null,
      "region_name": null,
      "tier": null,
      "usecases": [
        "verify"
      ],
      "version": "2011"
    }
  },
  {
    "sourceData": {
      "back_required": true,
      "common_name": null,
      "country": "Finland | Suomi",
      "country_alpha2": "FI",
      "country_alpha3": "FIN",
      "document_type": "REP",
      "has_nfc": false,
      "id": 10425,
      "municipality": null,
      "region_iso": null,
      "region_name": null,
      "tier": "tier1",
      "usecases": [
        "verify"
      ],
      "version": "2020 1"
    }
  },
  {
    "sourceData": {
      "back_required": true,
      "common_name": null,
      "country": "France",
      "country_alpha2": "FR",
      "country_alpha3": "FRA",
      "document_type": "REP",
      "has_nfc": true,
      "id": 5126,
      "municipality": null,
      "region_iso": null,
      "region_name": null,
      "tier": null,
      "usecases": [
        "verify"
      ],
      "version": "2002"
    }
  },
  {
    "sourceData": {
      "back_required": true,
      "common_name": null,
      "country": "France",
      "country_alpha2": "FR",
      "country_alpha3": "FRA",
      "document_type": "REP",
      "has_nfc": true,
      "id": 6623,
      "municipality": null,
      "region_iso": null,
      "region_name": null,
      "tier": null,
      "usecases": [
        "verify"
      ],
      "version": "2011"
    }
  },
  {
    "sourceData": {
      "back_required": true,
      "common_name": null,
      "country": "France",
      "country_alpha2": "FR",
      "country_alpha3": "FRA",
      "document_type": "REP",
      "has_nfc": true,
      "id": 9727,
      "municipality": null,
      "region_iso": null,
      "region_name": null,
      "tier": "tier1",
      "usecases": [
        "verify"
      ],
      "version": "2020"
    }
  },
  {
    "sourceData": {
      "back_required": true,
      "common_name": null,
      "country": "Georgia | საქართველო",
      "country_alpha2": "GE",
      "country_alpha3": "GEO",
      "document_type": "REP",
      "has_nfc": false,
      "id": 9857,
      "municipality": null,
      "region_iso": null,
      "region_name": null,
      "tier": null,
      "usecases": [
        "verify"
      ],
      "version": "2011"
    }
  },
  {
    "sourceData": {
      "back_required": false,
      "common_name": null,
      "country": "Germany | Deutschland",
      "country_alpha2": "DE",
      "country_alpha3": "DEU",
      "document_type": "REP",
      "has_nfc": true,
      "id": 4111,
      "municipality": null,
      "region_iso": null,
      "region_name": null,
      "tier": null,
      "usecases": [
        "verify"
      ],
      "version": "2011"
    }
  },
  {
    "sourceData": {
      "back_required": true,
      "common_name": null,
      "country": "Germany | Deutschland",
      "country_alpha2": "DE",
      "country_alpha3": "DEU",
      "document_type": "REP",
      "has_nfc": true,
      "id": 6076,
      "municipality": null,
      "region_iso": null,
      "region_name": null,
      "tier": null,
      "usecases": [
        "verify"
      ],
      "version": "2019"
    }
  },
  {
    "sourceData": {
      "back_required": false,
      "common_name": null,
      "country": "Germany | Deutschland",
      "country_alpha2": "DE",
      "country_alpha3": "DEU",
      "document_type": "REP",
      "has_nfc": false,
      "id": 10040,
      "municipality": null,
      "region_iso": null,
      "region_name": null,
      "tier": "tier1",
      "usecases": [
        "verify"
      ],
      "version": "1997"
    }
  },
  {
    "sourceData": {
      "back_required": true,
      "common_name": null,
      "country": "Germany | Deutschland",
      "country_alpha2": "DE",
      "country_alpha3": "DEU",
      "document_type": "REP",
      "has_nfc": true,
      "id": 10337,
      "municipality": null,
      "region_iso": null,
      "region_name": null,
      "tier": null,
      "usecases": [
        "verify"
      ],
      "version": "2019 1"
    }
  },
  {
    "sourceData": {
      "back_required": false,
      "common_name": null,
      "country": "Germany | Deutschland",
      "country_alpha2": "DE",
      "country_alpha3": "DEU",
      "document_type": "REP",
      "has_nfc": false,
      "id": 6075,
      "municipality": null,
      "region_iso": null,
      "region_name": null,
      "tier": "tier2",
      "usecases": [
        "verify"
      ],
      "version": "2011 2"
    }
  },
  {
    "sourceData": {
      "back_required": false,
      "common_name": null,
      "country": "Germany | Deutschland",
      "country_alpha2": "DE",
      "country_alpha3": "DEU",
      "document_type": "REP",
      "has_nfc": false,
      "id": 8867,
      "municipality": null,
      "region_iso": null,
      "region_name": null,
      "tier": "tier3",
      "usecases": [
        "verify"
      ],
      "version": "2011 1"
    }
  },
  {
    "sourceData": {
      "back_required": false,
      "common_name": null,
      "country": "Germany | Deutschland",
      "country_alpha2": "DE",
      "country_alpha3": "DEU",
      "document_type": "REP",
      "has_nfc": false,
      "id": 4293,
      "municipality": null,
      "region_iso": null,
      "region_name": null,
      "tier": null,
      "usecases": [
        "verify"
      ],
      "version": "2005"
    }
  },
  {
    "sourceData": {
      "back_required": false,
      "common_name": null,
      "country": "Germany | Deutschland",
      "country_alpha2": "DE",
      "country_alpha3": "DEU",
      "document_type": "REP",
      "has_nfc": false,
      "id": 4296,
      "municipality": null,
      "region_iso": null,
      "region_name": null,
      "tier": null,
      "usecases": [
        "verify"
      ],
      "version": "2007"
    }
  },
  {
    "sourceData": {
      "back_required": true,
      "common_name": null,
      "country": "Greece | Ελλάδα",
      "country_alpha2": "GR",
      "country_alpha3": "GRC",
      "document_type": "REP",
      "has_nfc": true,
      "id": 6081,
      "municipality": null,
      "region_iso": null,
      "region_name": null,
      "tier": null,
      "usecases": [
        "verify"
      ],
      "version": "2013"
    }
  },
  {
    "sourceData": {
      "back_required": false,
      "common_name": null,
      "country": "Greece | Ελλάδα",
      "country_alpha2": "GR",
      "country_alpha3": "GRC",
      "document_type": "REP",
      "has_nfc": true,
      "id": 9527,
      "municipality": null,
      "region_iso": null,
      "region_name": null,
      "tier": "tier1",
      "usecases": [
        "verify"
      ],
      "version": "2020"
    }
  },
  {
    "sourceData": {
      "back_required": false,
      "common_name": null,
      "country": "Haiti | Haïti",
      "country_alpha2": "HT",
      "country_alpha3": "HTI",
      "document_type": "REP",
      "has_nfc": false,
      "id": 9965,
      "municipality": null,
      "region_iso": null,
      "region_name": null,
      "tier": null,
      "usecases": [
        "verify"
      ],
      "version": "2009"
    }
  },
  {
    "sourceData": {
      "back_required": true,
      "common_name": null,
      "country": "Hungary | Magyarország",
      "country_alpha2": "HU",
      "country_alpha3": "HUN",
      "document_type": "REP",
      "id": 6083,
      "region_iso": null,
      "usecases": [
        "verify"
      ],
      "version": null
    }
  },
  {
    "sourceData": {
      "back_required": true,
      "common_name": null,
      "country": "Hungary | Magyarország",
      "country_alpha2": "HU",
      "country_alpha3": "HUN",
      "document_type": "REP",
      "id": 6084,
      "region_iso": null,
      "usecases": [
        "verify"
      ],
      "version": null
    }
  },
  {
    "sourceData": {
      "back_required": true,
      "common_name": null,
      "country": "Hungary | Magyarország",
      "country_alpha2": "HU",
      "country_alpha3": "HUN",
      "document_type": "REP",
      "has_nfc": false,
      "id": 4572,
      "municipality": null,
      "region_iso": null,
      "region_name": null,
      "tier": null,
      "usecases": [
        "verify"
      ],
      "version": "2003"
    }
  },
  {
    "sourceData": {
      "back_required": true,
      "common_name": null,
      "country": "Hungary | Magyarország",
      "country_alpha2": "HU",
      "country_alpha3": "HUN",
      "document_type": "REP",
      "has_nfc": false,
      "id": 4573,
      "municipality": null,
      "region_iso": null,
      "region_name": null,
      "tier": null,
      "usecases": [
        "verify"
      ],
      "version": "2007"
    }
  },
  {
    "sourceData": {
      "back_required": true,
      "common_name": null,
      "country": "Hungary | Magyarország",
      "country_alpha2": "HU",
      "country_alpha3": "HUN",
      "document_type": "REP",
      "has_nfc": true,
      "id": 4574,
      "municipality": null,
      "region_iso": null,
      "region_name": null,
      "tier": null,
      "usecases": [
        "verify"
      ],
      "version": "2008"
    }
  },
  {
    "sourceData": {
      "back_required": true,
      "common_name": null,
      "country": "Hungary | Magyarország",
      "country_alpha2": "HU",
      "country_alpha3": "HUN",
      "document_type": "REP",
      "has_nfc": true,
      "id": 4575,
      "municipality": null,
      "region_iso": null,
      "region_name": null,
      "tier": null,
      "usecases": [
        "verify"
      ],
      "version": "2011"
    }
  },
  {
    "sourceData": {
      "back_required": true,
      "common_name": null,
      "country": "Hungary | Magyarország",
      "country_alpha2": "HU",
      "country_alpha3": "HUN",
      "document_type": "REP",
      "has_nfc": true,
      "id": 4576,
      "municipality": null,
      "region_iso": null,
      "region_name": null,
      "tier": null,
      "usecases": [
        "verify"
      ],
      "version": "2012"
    }
  },
  {
    "sourceData": {
      "back_required": true,
      "common_name": null,
      "country": "Hungary | Magyarország",
      "country_alpha2": "HU",
      "country_alpha3": "HUN",
      "document_type": "REP",
      "has_nfc": false,
      "id": 4577,
      "municipality": null,
      "region_iso": null,
      "region_name": null,
      "tier": null,
      "usecases": [
        "verify"
      ],
      "version": "2013"
    }
  },
  {
    "sourceData": {
      "back_required": true,
      "common_name": null,
      "country": "Hungary | Magyarország",
      "country_alpha2": "HU",
      "country_alpha3": "HUN",
      "document_type": "REP",
      "has_nfc": true,
      "id": 4578,
      "municipality": null,
      "region_iso": null,
      "region_name": null,
      "tier": null,
      "usecases": [
        "verify"
      ],
      "version": "2016"
    }
  },
  {
    "sourceData": {
      "back_required": false,
      "common_name": null,
      "country": "Hungary | Magyarország",
      "country_alpha2": "HU",
      "country_alpha3": "HUN",
      "document_type": "REP",
      "has_nfc": true,
      "id": 8010,
      "municipality": null,
      "region_iso": null,
      "region_name": null,
      "tier": null,
      "usecases": [
        "verify"
      ],
      "version": "2016 2"
    }
  },
  {
    "sourceData": {
      "back_required": false,
      "common_name": null,
      "country": "Hungary | Magyarország",
      "country_alpha2": "HU",
      "country_alpha3": "HUN",
      "document_type": "REP",
      "has_nfc": true,
      "id": 8933,
      "municipality": null,
      "region_iso": null,
      "region_name": null,
      "tier": "tier1",
      "usecases": [
        "verify"
      ],
      "version": "2020"
    }
  },
  {
    "sourceData": {
      "back_required": true,
      "common_name": null,
      "country": "Iceland | Ísland",
      "country_alpha2": "IS",
      "country_alpha3": "ISL",
      "document_type": "REP",
      "has_nfc": false,
      "id": 9864,
      "municipality": null,
      "region_iso": null,
      "region_name": null,
      "tier": null,
      "usecases": [
        "verify"
      ],
      "version": "2007"
    }
  },
  {
    "sourceData": {
      "back_required": true,
      "common_name": null,
      "country": "Indonesia",
      "country_alpha2": "ID",
      "country_alpha3": "IDN",
      "document_type": "REP",
      "has_nfc": false,
      "id": 9966,
      "municipality": null,
      "region_iso": null,
      "region_name": null,
      "tier": "tier3",
      "usecases": [
        "verify"
      ],
      "version": null
    }
  },
  {
    "sourceData": {
      "back_required": true,
      "common_name": null,
      "country": "Ireland | Éire",
      "country_alpha2": "IE",
      "country_alpha3": "IRL",
      "document_type": "REP",
      "id": 4133,
      "region_iso": null,
      "usecases": [
        "verify"
      ],
      "version": null
    }
  },
  {
    "sourceData": {
      "back_required": true,
      "common_name": "",
      "country": "Ireland | Éire",
      "country_alpha2": "IE",
      "country_alpha3": "IRL",
      "document_type": "REP",
      "has_nfc": false,
      "id": 3431,
      "municipality": null,
      "region_iso": null,
      "region_name": null,
      "tier": null,
      "usecases": [
        "verify"
      ],
      "version": "2009 1"
    }
  },
  {
    "sourceData": {
      "back_required": true,
      "common_name": null,
      "country": "Ireland | Éire",
      "country_alpha2": "IE",
      "country_alpha3": "IRL",
      "document_type": "REP",
      "has_nfc": true,
      "id": 4134,
      "municipality": null,
      "region_iso": null,
      "region_name": null,
      "tier": null,
      "usecases": [
        "verify"
      ],
      "version": "2017"
    }
  },
  {
    "sourceData": {
      "back_required": false,
      "common_name": null,
      "country": "Ireland | Éire",
      "country_alpha2": "IE",
      "country_alpha3": "IRL",
      "document_type": "REP",
      "has_nfc": false,
      "id": 7452,
      "municipality": null,
      "region_iso": null,
      "region_name": null,
      "tier": null,
      "usecases": [
        "verify"
      ],
      "version": "2004"
    }
  },
  {
    "sourceData": {
      "back_required": true,
      "common_name": null,
      "country": "Ireland | Éire",
      "country_alpha2": "IE",
      "country_alpha3": "IRL",
      "document_type": "REP",
      "has_nfc": false,
      "id": 7453,
      "municipality": null,
      "region_iso": null,
      "region_name": null,
      "tier": null,
      "usecases": [
        "verify"
      ],
      "version": "2014"
    }
  },
  {
    "sourceData": {
      "back_required": false,
      "common_name": null,
      "country": "Italy | Italia",
      "country_alpha2": "IT",
      "country_alpha3": "ITA",
      "document_type": "REP",
      "has_nfc": false,
      "id": 4595,
      "municipality": null,
      "region_iso": null,
      "region_name": null,
      "tier": null,
      "usecases": [
        "verify"
      ],
      "version": "2018"
    }
  },
  {
    "sourceData": {
      "back_required": false,
      "common_name": null,
      "country": "Italy | Italia",
      "country_alpha2": "IT",
      "country_alpha3": "ITA",
      "document_type": "REP",
      "has_nfc": false,
      "id": 4596,
      "municipality": null,
      "region_iso": null,
      "region_name": null,
      "tier": null,
      "usecases": [
        "verify"
      ],
      "version": "2015"
    }
  },
  {
    "sourceData": {
      "back_required": false,
      "common_name": null,
      "country": "Italy | Italia",
      "country_alpha2": "IT",
      "country_alpha3": "ITA",
      "document_type": "REP",
      "has_nfc": false,
      "id": 8113,
      "municipality": null,
      "region_iso": null,
      "region_name": null,
      "tier": null,
      "usecases": [
        "verify"
      ],
      "version": "2007-3"
    }
  },
  {
    "sourceData": {
      "back_required": false,
      "common_name": null,
      "country": "Italy | Italia",
      "country_alpha2": "IT",
      "country_alpha3": "ITA",
      "document_type": "REP",
      "has_nfc": false,
      "id": 8112,
      "municipality": null,
      "region_iso": null,
      "region_name": null,
      "tier": null,
      "usecases": [
        "verify"
      ],
      "version": "2007-2"
    }
  },
  {
    "sourceData": {
      "back_required": true,
      "common_name": null,
      "country": "Italy | Italia",
      "country_alpha2": "IT",
      "country_alpha3": "ITA",
      "document_type": "REP",
      "has_nfc": false,
      "id": 10440,
      "municipality": null,
      "region_iso": null,
      "region_name": null,
      "tier": "tier1",
      "usecases": [
        "verify"
      ],
      "version": "2021"
    }
  },
  {
    "sourceData": {
      "back_required": true,
      "common_name": null,
      "country": "Italy | Italia",
      "country_alpha2": "IT",
      "country_alpha3": "ITA",
      "document_type": "REP",
      "has_nfc": true,
      "id": 3451,
      "municipality": null,
      "region_iso": null,
      "region_name": null,
      "tier": null,
      "usecases": [
        "verify"
      ],
      "version": "2013"
    }
  },
  {
    "sourceData": {
      "back_required": true,
      "common_name": null,
      "country": "Italy | Italia",
      "country_alpha2": "IT",
      "country_alpha3": "ITA",
      "document_type": "REP",
      "has_nfc": false,
      "id": 4551,
      "municipality": null,
      "region_iso": null,
      "region_name": null,
      "tier": null,
      "usecases": [
        "verify"
      ],
      "version": "2007"
    }
  },
  {
    "sourceData": {
      "back_required": false,
      "common_name": null,
      "country": "Japan | 日本",
      "country_alpha2": "JP",
      "country_alpha3": "JPN",
      "document_type": "REP",
      "has_nfc": false,
      "id": 5154,
      "municipality": null,
      "region_iso": null,
      "region_name": null,
      "tier": null,
      "usecases": [
        "verify"
      ],
      "version": null
    }
  },
  {
    "sourceData": {
      "back_required": true,
      "common_name": null,
      "country": "Kosovo, Republic of",
      "country_alpha2": "XK",
      "country_alpha3": "RKS",
      "document_type": "REP",
      "has_nfc": true,
      "id": 9866,
      "municipality": null,
      "region_iso": null,
      "region_name": null,
      "tier": null,
      "usecases": [
        "verify"
      ],
      "version": "2013"
    }
  },
  {
    "sourceData": {
      "back_required": true,
      "common_name": null,
      "country": "Latvia | Latvija",
      "country_alpha2": "LV",
      "country_alpha3": "LVA",
      "document_type": "REP",
      "has_nfc": true,
      "id": 4792,
      "municipality": null,
      "region_iso": null,
      "region_name": null,
      "tier": null,
      "usecases": [
        "verify"
      ],
      "version": "2012"
    }
  },
  {
    "sourceData": {
      "back_required": true,
      "common_name": null,
      "country": "Latvia | Latvija",
      "country_alpha2": "LV",
      "country_alpha3": "LVA",
      "document_type": "REP",
      "has_nfc": false,
      "id": 10244,
      "municipality": null,
      "region_iso": null,
      "region_name": null,
      "tier": "tier1",
      "usecases": [
        "verify"
      ],
      "version": "2021"
    }
  },
  {
    "sourceData": {
      "back_required": true,
      "common_name": null,
      "country": "Latvia | Latvija",
      "country_alpha2": "LV",
      "country_alpha3": "LVA",
      "document_type": "REP",
      "has_nfc": false,
      "id": 10438,
      "municipality": null,
      "region_iso": null,
      "region_name": null,
      "tier": "tier1",
      "usecases": [
        "verify"
      ],
      "version": "2021"
    }
  },
  {
    "sourceData": {
      "back_required": false,
      "common_name": null,
      "country": "Latvia | Latvija",
      "country_alpha2": "LV",
      "country_alpha3": "LVA",
      "data_validation_reviewed": true,
      "document_type": "REP",
      "has_nfc": false,
      "id": 8373,
      "municipality": null,
      "region_iso": null,
      "region_name": null,
      "sop_status": "REVIEWED",
      "tier": "tier1",
      "usecases": [
        "verify"
      ],
      "version": "2019"
    }
  },
  {
    "sourceData": {
      "back_required": true,
      "common_name": null,
      "country": "Latvia | Latvija",
      "country_alpha2": "LV",
      "country_alpha3": "LVA",
      "data_validation_reviewed": true,
      "document_type": "REP",
      "has_nfc": true,
      "id": 10439,
      "municipality": null,
      "region_iso": null,
      "region_name": null,
      "sop_status": "REVIEWED",
      "tier": "tier1",
      "usecases": [
        "verify"
      ],
      "version": "2016"
    }
  },
  {
    "sourceData": {
      "back_required": true,
      "common_name": null,
      "country": "Lebanon | لبنان",
      "country_alpha2": "LB",
      "country_alpha3": "LBN",
      "document_type": "REP",
      "has_nfc": false,
      "id": 10377,
      "municipality": null,
      "region_iso": null,
      "region_name": null,
      "tier": "tier2",
      "usecases": [
        "verify"
      ],
      "version": "1"
    }
  },
  {
    "sourceData": {
      "back_required": true,
      "common_name": null,
      "country": "Liechtenstein",
      "country_alpha2": "LI",
      "country_alpha3": "LIE",
      "document_type": "REP",
      "has_nfc": false,
      "id": 5131,
      "municipality": null,
      "region_iso": null,
      "region_name": null,
      "tier": null,
      "usecases": [
        "verify"
      ],
      "version": "2009"
    }
  },
  {
    "sourceData": {
      "back_required": true,
      "common_name": null,
      "country": "Lithuania | Lietuva",
      "country_alpha2": "LT",
      "country_alpha3": "LTU",
      "document_type": "REP",
      "has_nfc": true,
      "id": 3563,
      "municipality": null,
      "region_iso": null,
      "region_name": null,
      "tier": null,
      "usecases": [
        "verify"
      ],
      "version": "2004"
    }
  },
  {
    "sourceData": {
      "back_required": true,
      "common_name": null,
      "country": "Lithuania | Lietuva",
      "country_alpha2": "LT",
      "country_alpha3": "LTU",
      "document_type": "REP",
      "has_nfc": true,
      "id": 3564,
      "municipality": null,
      "region_iso": null,
      "region_name": null,
      "tier": null,
      "usecases": [
        "verify"
      ],
      "version": "2011"
    }
  },
  {
    "sourceData": {
      "back_required": false,
      "common_name": null,
      "country": "Lithuania | Lietuva",
      "country_alpha2": "LT",
      "country_alpha3": "LTU",
      "document_type": "REP",
      "has_nfc": true,
      "id": 4891,
      "municipality": null,
      "region_iso": null,
      "region_name": null,
      "tier": null,
      "usecases": [
        "verify"
      ],
      "version": "2011"
    }
  },
  {
    "sourceData": {
      "back_required": true,
      "common_name": null,
      "country": "Lithuania | Lietuva",
      "country_alpha2": "LT",
      "country_alpha3": "LTU",
      "document_type": "REP",
      "has_nfc": false,
      "id": 4892,
      "municipality": null,
      "region_iso": null,
      "region_name": null,
      "tier": null,
      "usecases": [
        "verify"
      ],
      "version": "2009"
    }
  },
  {
    "sourceData": {
      "back_required": true,
      "common_name": null,
      "country": "Lithuania | Lietuva",
      "country_alpha2": "LT",
      "country_alpha3": "LTU",
      "document_type": "REP",
      "has_nfc": true,
      "id": 9297,
      "municipality": null,
      "region_iso": null,
      "region_name": null,
      "tier": "tier1",
      "usecases": [
        "verify"
      ],
      "version": "2020"
    }
  },
  {
    "sourceData": {
      "back_required": true,
      "common_name": null,
      "country": "Luxembourg | Luxemburg",
      "country_alpha2": "LU",
      "country_alpha3": "LUX",
      "document_type": "REP",
      "has_nfc": true,
      "id": 5132,
      "municipality": null,
      "region_iso": null,
      "region_name": null,
      "tier": null,
      "usecases": [
        "verify"
      ],
      "version": "2011"
    }
  },
  {
    "sourceData": {
      "back_required": true,
      "common_name": null,
      "country": "Luxembourg | Luxemburg",
      "country_alpha2": "LU",
      "country_alpha3": "LUX",
      "document_type": "REP",
      "has_nfc": false,
      "id": 10385,
      "municipality": null,
      "region_iso": null,
      "region_name": null,
      "tier": "tier1",
      "usecases": [
        "verify"
      ],
      "version": "2020"
    }
  },
  {
    "sourceData": {
      "back_required": true,
      "common_name": null,
      "country": "Macao | 澳門",
      "country_alpha2": "MO",
      "country_alpha3": "MAC",
      "document_type": "REP",
      "has_nfc": false,
      "id": 3581,
      "municipality": null,
      "region_iso": null,
      "region_name": null,
      "tier": null,
      "usecases": [
        "verify"
      ],
      "version": "2002"
    }
  },
  {
    "sourceData": {
      "back_required": true,
      "common_name": null,
      "country": "Macao | 澳門",
      "country_alpha2": "MO",
      "country_alpha3": "MAC",
      "document_type": "REP",
      "has_nfc": false,
      "id": 3582,
      "municipality": null,
      "region_iso": null,
      "region_name": null,
      "tier": null,
      "usecases": [
        "verify"
      ],
      "version": "2013"
    }
  },
  {
    "sourceData": {
      "back_required": true,
      "common_name": null,
      "country": "Macedonia (the former Yugoslav Republic of) | Македонија",
      "country_alpha2": "MK",
      "country_alpha3": "MKD",
      "document_type": "REP",
      "has_nfc": false,
      "id": 3589,
      "municipality": null,
      "region_iso": null,
      "region_name": null,
      "tier": null,
      "usecases": [
        "verify"
      ],
      "version": "2008"
    }
  },
  {
    "sourceData": {
      "back_required": true,
      "common_name": null,
      "country": "Macedonia (the former Yugoslav Republic of) | Македонија",
      "country_alpha2": "MK",
      "country_alpha3": "MKD",
      "document_type": "REP",
      "has_nfc": false,
      "id": 6111,
      "municipality": null,
      "region_iso": null,
      "region_name": null,
      "tier": null,
      "usecases": [
        "verify"
      ],
      "version": "2008-2"
    }
  },
  {
    "sourceData": {
      "back_required": true,
      "common_name": null,
      "country": "Malaysia",
      "country_alpha2": "MY",
      "country_alpha3": "MYS",
      "document_type": "REP",
      "has_nfc": false,
      "id": 5159,
      "municipality": null,
      "region_iso": null,
      "region_name": null,
      "tier": null,
      "usecases": [
        "verify"
      ],
      "version": "1"
    }
  },
  {
    "sourceData": {
      "back_required": true,
      "common_name": null,
      "country": "Malta",
      "country_alpha2": "MT",
      "country_alpha3": "MLT",
      "document_type": "REP",
      "id": 6112,
      "region_iso": null,
      "usecases": [
        "verify"
      ],
      "version": "2004"
    }
  },
  {
    "sourceData": {
      "back_required": true,
      "common_name": null,
      "country": "Malta",
      "country_alpha2": "MT",
      "country_alpha3": "MLT",
      "document_type": "REP",
      "has_nfc": false,
      "id": 4775,
      "municipality": null,
      "region_iso": null,
      "region_name": null,
      "tier": null,
      "usecases": [
        "verify"
      ],
      "version": "2014"
    }
  },
  {
    "sourceData": {
      "back_required": true,
      "common_name": null,
      "country": "Malta",
      "country_alpha2": "MT",
      "country_alpha3": "MLT",
      "document_type": "REP",
      "has_nfc": false,
      "id": 7547,
      "municipality": null,
      "region_iso": null,
      "region_name": null,
      "tier": "tier1",
      "usecases": [
        "verify"
      ],
      "version": "2020"
    }
  },
  {
    "sourceData": {
      "back_required": true,
      "common_name": null,
      "country": "Malta",
      "country_alpha2": "MT",
      "country_alpha3": "MLT",
      "document_type": "REP",
      "has_nfc": false,
      "id": 10435,
      "municipality": null,
      "region_iso": null,
      "region_name": null,
      "tier": "tier1",
      "usecases": [
        "verify"
      ],
      "version": "2021"
    }
  },
  {
    "sourceData": {
      "back_required": true,
      "common_name": null,
      "country": "Malta",
      "country_alpha2": "MT",
      "country_alpha3": "MLT",
      "document_type": "REP",
      "has_nfc": true,
      "id": 10461,
      "municipality": null,
      "region_iso": null,
      "region_name": null,
      "tier": "tier3",
      "usecases": [
        "verify"
      ],
      "version": "2021 document"
    }
  },
  {
    "sourceData": {
      "back_required": true,
      "common_name": null,
      "country": "Mexico | México",
      "country_alpha2": "MX",
      "country_alpha3": "MEX",
      "document_type": "REP",
      "has_nfc": false,
      "id": 9970,
      "municipality": null,
      "region_iso": null,
      "region_name": null,
      "tier": "tier2",
      "usecases": [
        "verify"
      ],
      "version": "2010 3"
    }
  },
  {
    "sourceData": {
      "back_required": true,
      "common_name": null,
      "country": "Mexico | México",
      "country_alpha2": "MX",
      "country_alpha3": "MEX",
      "document_type": "REP",
      "has_nfc": false,
      "id": 9971,
      "municipality": null,
      "region_iso": null,
      "region_name": null,
      "tier": "tier2",
      "usecases": [
        "verify"
      ],
      "version": "2010 2"
    }
  },
  {
    "sourceData": {
      "back_required": true,
      "common_name": null,
      "country": "Mexico | México",
      "country_alpha2": "MX",
      "country_alpha3": "MEX",
      "document_type": "REP",
      "has_nfc": false,
      "id": 9972,
      "municipality": null,
      "region_iso": null,
      "region_name": null,
      "tier": "tier2",
      "usecases": [
        "verify"
      ],
      "version": "2010 1"
    }
  },
  {
    "sourceData": {
      "back_required": true,
      "common_name": null,
      "country": "Mexico | México",
      "country_alpha2": "MX",
      "country_alpha3": "MEX",
      "document_type": "REP",
      "has_nfc": false,
      "id": 10211,
      "municipality": null,
      "region_iso": null,
      "region_name": null,
      "tier": "tier2",
      "usecases": [
        "verify"
      ],
      "version": "5"
    }
  },
  {
    "sourceData": {
      "back_required": true,
      "common_name": null,
      "country": "Mexico | México",
      "country_alpha2": "MX",
      "country_alpha3": "MEX",
      "document_type": "REP",
      "has_nfc": false,
      "id": 10370,
      "municipality": null,
      "region_iso": null,
      "region_name": null,
      "tier": "tier2",
      "usecases": [
        "verify"
      ],
      "version": "2010 4"
    }
  },
  {
    "sourceData": {
      "back_required": true,
      "common_name": null,
      "country": "Mexico | México",
      "country_alpha2": "MX",
      "country_alpha3": "MEX",
      "document_type": "REP",
      "has_nfc": false,
      "id": 10371,
      "municipality": null,
      "region_iso": null,
      "region_name": null,
      "tier": "tier2",
      "usecases": [
        "verify"
      ],
      "version": "6"
    }
  },
  {
    "sourceData": {
      "back_required": true,
      "common_name": null,
      "country": "Mexico | México",
      "country_alpha2": "MX",
      "country_alpha3": "MEX",
      "document_type": "REP",
      "has_nfc": false,
      "id": 10372,
      "municipality": null,
      "region_iso": null,
      "region_name": null,
      "tier": "tier2",
      "usecases": [
        "verify"
      ],
      "version": "7"
    }
  },
  {
    "sourceData": {
      "back_required": true,
      "common_name": null,
      "country": "Moldova (Republic of)",
      "country_alpha2": "MD",
      "country_alpha3": "MDA",
      "document_type": "REP",
      "has_nfc": false,
      "id": 3646,
      "municipality": null,
      "region_iso": null,
      "region_name": null,
      "tier": null,
      "usecases": [
        "verify"
      ],
      "version": "2013"
    }
  },
  {
    "sourceData": {
      "back_required": true,
      "common_name": null,
      "country": "Moldova (Republic of)",
      "country_alpha2": "MD",
      "country_alpha3": "MDA",
      "document_type": "REP",
      "has_nfc": false,
      "id": 3647,
      "municipality": null,
      "region_iso": null,
      "region_name": null,
      "tier": null,
      "usecases": [
        "verify"
      ],
      "version": "2016"
    }
  },
  {
    "sourceData": {
      "back_required": true,
      "common_name": null,
      "country": "Moldova (Republic of)",
      "country_alpha2": "MD",
      "country_alpha3": "MDA",
      "document_type": "REP",
      "has_nfc": false,
      "id": 6116,
      "municipality": null,
      "region_iso": null,
      "region_name": null,
      "tier": null,
      "usecases": [
        "verify"
      ],
      "version": "2013"
    }
  },
  {
    "sourceData": {
      "back_required": false,
      "common_name": null,
      "country": "Moldova (Republic of)",
      "country_alpha2": "MD",
      "country_alpha3": "MDA",
      "document_type": "REP",
      "has_nfc": false,
      "id": 6117,
      "municipality": null,
      "region_iso": null,
      "region_name": null,
      "tier": null,
      "usecases": [
        "verify"
      ],
      "version": "2015"
    }
  },
  {
    "sourceData": {
      "back_required": true,
      "common_name": null,
      "country": "Monaco",
      "country_alpha2": "MC",
      "country_alpha3": "MCO",
      "document_type": "REP",
      "has_nfc": false,
      "id": 6118,
      "municipality": null,
      "region_iso": null,
      "region_name": null,
      "tier": null,
      "usecases": [
        "verify"
      ],
      "version": null
    }
  },
  {
    "sourceData": {
      "back_required": true,
      "common_name": null,
      "country": "Monaco",
      "country_alpha2": "MC",
      "country_alpha3": "MCO",
      "document_type": "REP",
      "has_nfc": false,
      "id": 10480,
      "municipality": null,
      "region_iso": null,
      "region_name": null,
      "tier": "tier1",
      "usecases": [
        "verify"
      ],
      "version": "2"
    }
  },
  {
    "sourceData": {
      "back_required": false,
      "common_name": null,
      "country": "Morocco | المغرب",
      "country_alpha2": "MA",
      "country_alpha3": "MAR",
      "document_type": "REP",
      "has_nfc": false,
      "id": 10203,
      "municipality": null,
      "region_iso": null,
      "region_name": null,
      "tier": null,
      "usecases": [
        "verify"
      ],
      "version": "1"
    }
  },
  {
    "sourceData": {
      "back_required": true,
      "common_name": null,
      "country": "Mozambique | Moçambique",
      "country_alpha2": "MZ",
      "country_alpha3": "MOZ",
      "document_type": "REP",
      "has_nfc": false,
      "id": 3666,
      "municipality": null,
      "region_iso": null,
      "region_name": null,
      "tier": null,
      "usecases": [
        "verify"
      ],
      "version": "2010"
    }
  },
  {
    "sourceData": {
      "back_required": true,
      "common_name": null,
      "country": "Namibia",
      "country_alpha2": "NA",
      "country_alpha3": "NAM",
      "document_type": "REP",
      "has_nfc": false,
      "id": 10090,
      "municipality": null,
      "region_iso": null,
      "region_name": null,
      "tier": null,
      "usecases": [
        "verify"
      ],
      "version": null
    }
  },
  {
    "sourceData": {
      "back_required": true,
      "common_name": null,
      "country": "Netherlands | Nederland",
      "country_alpha2": "NL",
      "country_alpha3": "NLD",
      "document_type": "REP",
      "has_nfc": false,
      "id": 3700,
      "municipality": null,
      "region_iso": null,
      "region_name": null,
      "tier": null,
      "usecases": [
        "verify"
      ],
      "version": "2014"
    }
  },
  {
    "sourceData": {
      "back_required": true,
      "common_name": null,
      "country": "Netherlands | Nederland",
      "country_alpha2": "NL",
      "country_alpha3": "NLD",
      "document_type": "REP",
      "has_nfc": true,
      "id": 9231,
      "municipality": null,
      "region_iso": null,
      "region_name": null,
      "tier": "tier1",
      "usecases": [
        "verify"
      ],
      "version": "2020"
    }
  },
  {
    "sourceData": {
      "back_required": true,
      "common_name": null,
      "country": "Norway | Norge",
      "country_alpha2": "NO",
      "country_alpha3": "NOR",
      "document_type": "REP",
      "has_nfc": true,
      "id": 5137,
      "municipality": null,
      "region_iso": null,
      "region_name": null,
      "tier": null,
      "usecases": [
        "verify"
      ],
      "version": "2017"
    }
  },
  {
    "sourceData": {
      "back_required": true,
      "common_name": null,
      "country": "Norway | Norge",
      "country_alpha2": "NO",
      "country_alpha3": "NOR",
      "document_type": "REP",
      "has_nfc": true,
      "id": 6121,
      "municipality": null,
      "region_iso": null,
      "region_name": null,
      "tier": null,
      "usecases": [
        "verify"
      ],
      "version": "2012"
    }
  },
  {
    "sourceData": {
      "back_required": true,
      "common_name": null,
      "country": "Norway | Norge",
      "country_alpha2": "NO",
      "country_alpha3": "NOR",
      "document_type": "REP",
      "has_nfc": true,
      "id": 6122,
      "municipality": null,
      "region_iso": null,
      "region_name": null,
      "tier": null,
      "usecases": [
        "verify"
      ],
      "version": "2017-2"
    }
  },
  {
    "sourceData": {
      "back_required": false,
      "common_name": null,
      "country": "Norway | Norge",
      "country_alpha2": "NO",
      "country_alpha3": "NOR",
      "document_type": "REP",
      "has_nfc": true,
      "id": 9461,
      "municipality": null,
      "region_iso": null,
      "region_name": null,
      "tier": null,
      "usecases": [
        "verify"
      ],
      "version": "2020"
    }
  },
  {
    "sourceData": {
      "back_required": true,
      "common_name": null,
      "country": "Oman | عمان",
      "country_alpha2": "OM",
      "country_alpha3": "OMN",
      "document_type": "REP",
      "has_nfc": false,
      "id": 3755,
      "municipality": null,
      "region_iso": null,
      "region_name": null,
      "tier": null,
      "usecases": [
        "verify"
      ],
      "version": "2013"
    }
  },
  {
    "sourceData": {
      "back_required": true,
      "common_name": null,
      "country": "Oman | عمان",
      "country_alpha2": "OM",
      "country_alpha3": "OMN",
      "document_type": "REP",
      "has_nfc": false,
      "id": 5920,
      "municipality": null,
      "region_iso": null,
      "region_name": null,
      "tier": null,
      "usecases": [
        "verify"
      ],
      "version": "2019"
    }
  },
  {
    "sourceData": {
      "back_required": false,
      "common_name": null,
      "country": "Panama | Panamá",
      "country_alpha2": "PA",
      "country_alpha3": "PAN",
      "document_type": "REP",
      "has_nfc": false,
      "id": 9889,
      "municipality": null,
      "region_iso": null,
      "region_name": null,
      "tier": null,
      "usecases": [
        "verify"
      ],
      "version": null
    }
  },
  {
    "sourceData": {
      "back_required": true,
      "common_name": null,
      "country": "Peru | Perú",
      "country_alpha2": "PE",
      "country_alpha3": "PER",
      "document_type": "REP",
      "has_nfc": false,
      "id": 8537,
      "municipality": null,
      "region_iso": null,
      "region_name": null,
      "tier": null,
      "usecases": [
        "verify"
      ],
      "version": "2018"
    }
  },
  {
    "sourceData": {
      "back_required": true,
      "common_name": null,
      "country": "Peru | Perú",
      "country_alpha2": "PE",
      "country_alpha3": "PER",
      "document_type": "REP",
      "has_nfc": false,
      "id": 8538,
      "municipality": null,
      "region_iso": null,
      "region_name": null,
      "tier": null,
      "usecases": [
        "verify"
      ],
      "version": "2011"
    }
  },
  {
    "sourceData": {
      "back_required": true,
      "common_name": null,
      "country": "Poland | Polska",
      "country_alpha2": "PL",
      "country_alpha3": "POL",
      "document_type": "REP",
      "has_nfc": true,
      "id": 3791,
      "municipality": null,
      "region_iso": null,
      "region_name": null,
      "tier": null,
      "usecases": [
        "verify"
      ],
      "version": "2011"
    }
  },
  {
    "sourceData": {
      "back_required": true,
      "common_name": null,
      "country": "Poland | Polska",
      "country_alpha2": "PL",
      "country_alpha3": "POL",
      "document_type": "REP",
      "has_nfc": true,
      "id": 4560,
      "municipality": null,
      "region_iso": null,
      "region_name": null,
      "tier": null,
      "usecases": [
        "verify"
      ],
      "version": "2014"
    }
  },
  {
    "sourceData": {
      "back_required": true,
      "common_name": null,
      "country": "Poland | Polska",
      "country_alpha2": "PL",
      "country_alpha3": "POL",
      "document_type": "REP",
      "has_nfc": true,
      "id": 4561,
      "municipality": null,
      "region_iso": null,
      "region_name": null,
      "tier": null,
      "usecases": [
        "verify"
      ],
      "version": "2004"
    }
  },
  {
    "sourceData": {
      "back_required": true,
      "common_name": null,
      "country": "Poland | Polska",
      "country_alpha2": "PL",
      "country_alpha3": "POL",
      "document_type": "REP",
      "has_nfc": true,
      "id": 4612,
      "municipality": null,
      "region_iso": null,
      "region_name": null,
      "tier": null,
      "usecases": [
        "verify"
      ],
      "version": "2014"
    }
  },
  {
    "sourceData": {
      "back_required": true,
      "common_name": null,
      "country": "Poland | Polska",
      "country_alpha2": "PL",
      "country_alpha3": "POL",
      "document_type": "REP",
      "has_nfc": false,
      "id": 4614,
      "municipality": null,
      "region_iso": null,
      "region_name": null,
      "tier": null,
      "usecases": [
        "verify"
      ],
      "version": "2001"
    }
  },
  {
    "sourceData": {
      "back_required": true,
      "common_name": null,
      "country": "Poland | Polska",
      "country_alpha2": "PL",
      "country_alpha3": "POL",
      "document_type": "REP",
      "has_nfc": false,
      "id": 4615,
      "municipality": null,
      "region_iso": null,
      "region_name": null,
      "tier": null,
      "usecases": [
        "verify"
      ],
      "version": "2012"
    }
  },
  {
    "sourceData": {
      "back_required": true,
      "common_name": null,
      "country": "Poland | Polska",
      "country_alpha2": "PL",
      "country_alpha3": "POL",
      "document_type": "REP",
      "has_nfc": false,
      "id": 4616,
      "municipality": null,
      "region_iso": null,
      "region_name": null,
      "tier": null,
      "usecases": [
        "verify"
      ],
      "version": "2012"
    }
  },
  {
    "sourceData": {
      "back_required": true,
      "common_name": null,
      "country": "Poland | Polska",
      "country_alpha2": "PL",
      "country_alpha3": "POL",
      "document_type": "REP",
      "has_nfc": false,
      "id": 4710,
      "municipality": null,
      "region_iso": null,
      "region_name": null,
      "tier": null,
      "usecases": [
        "verify"
      ],
      "version": "2001"
    }
  },
  {
    "sourceData": {
      "back_required": true,
      "common_name": null,
      "country": "Poland | Polska",
      "country_alpha2": "PL",
      "country_alpha3": "POL",
      "document_type": "REP",
      "has_nfc": true,
      "id": 4711,
      "municipality": null,
      "region_iso": null,
      "region_name": null,
      "tier": null,
      "usecases": [
        "verify"
      ],
      "version": "2004"
    }
  },
  {
    "sourceData": {
      "back_required": false,
      "common_name": null,
      "country": "Poland | Polska",
      "country_alpha2": "PL",
      "country_alpha3": "POL",
      "document_type": "REP",
      "has_nfc": false,
      "id": 4712,
      "municipality": null,
      "region_iso": null,
      "region_name": null,
      "tier": null,
      "usecases": [
        "verify"
      ],
      "version": "2007"
    }
  },
  {
    "sourceData": {
      "back_required": false,
      "common_name": null,
      "country": "Poland | Polska",
      "country_alpha2": "PL",
      "country_alpha3": "POL",
      "document_type": "REP",
      "has_nfc": false,
      "id": 4713,
      "municipality": null,
      "region_iso": null,
      "region_name": null,
      "tier": null,
      "usecases": [
        "verify"
      ],
      "version": "2007"
    }
  },
  {
    "sourceData": {
      "back_required": true,
      "common_name": null,
      "country": "Poland | Polska",
      "country_alpha2": "PL",
      "country_alpha3": "POL",
      "document_type": "REP",
      "has_nfc": true,
      "id": 4714,
      "municipality": null,
      "region_iso": null,
      "region_name": null,
      "tier": null,
      "usecases": [
        "verify"
      ],
      "version": "2014"
    }
  },
  {
    "sourceData": {
      "back_required": true,
      "common_name": null,
      "country": "Poland | Polska",
      "country_alpha2": "PL",
      "country_alpha3": "POL",
      "document_type": "REP",
      "has_nfc": true,
      "id": 9298,
      "municipality": null,
      "region_iso": null,
      "region_name": null,
      "tier": "tier1",
      "usecases": [
        "verify"
      ],
      "version": "2020"
    }
  },
  {
    "sourceData": {
      "back_required": true,
      "common_name": null,
      "country": "Portugal",
      "country_alpha2": "PT",
      "country_alpha3": "PRT",
      "document_type": "REP",
      "has_nfc": true,
      "id": 4562,
      "municipality": null,
      "region_iso": null,
      "region_name": null,
      "tier": null,
      "usecases": [
        "verify"
      ],
      "version": "2008"
    }
  },
  {
    "sourceData": {
      "back_required": true,
      "common_name": null,
      "country": "Portugal",
      "country_alpha2": "PT",
      "country_alpha3": "PRT",
      "document_type": "REP",
      "has_nfc": true,
      "id": 4563,
      "municipality": null,
      "region_iso": null,
      "region_name": null,
      "tier": null,
      "usecases": [
        "verify"
      ],
      "version": "2017"
    }
  },
  {
    "sourceData": {
      "back_required": true,
      "common_name": null,
      "country": "Portugal",
      "country_alpha2": "PT",
      "country_alpha3": "PRT",
      "document_type": "REP",
      "has_nfc": false,
      "id": 4709,
      "municipality": null,
      "region_iso": null,
      "region_name": null,
      "tier": null,
      "usecases": [
        "verify"
      ],
      "version": "2019"
    }
  },
  {
    "sourceData": {
      "back_required": true,
      "common_name": null,
      "country": "Portugal",
      "country_alpha2": "PT",
      "country_alpha3": "PRT",
      "document_type": "REP",
      "has_nfc": false,
      "id": 8174,
      "municipality": null,
      "region_iso": null,
      "region_name": null,
      "tier": "tier1",
      "usecases": [
        "verify"
      ],
      "version": "2019"
    }
  },
  {
    "sourceData": {
      "back_required": true,
      "common_name": null,
      "country": "Portugal",
      "country_alpha2": "PT",
      "country_alpha3": "PRT",
      "document_type": "REP",
      "has_nfc": true,
      "id": 9296,
      "municipality": null,
      "region_iso": null,
      "region_name": null,
      "tier": "tier1",
      "usecases": [
        "verify"
      ],
      "version": "2020"
    }
  },
  {
    "sourceData": {
      "back_required": true,
      "common_name": null,
      "country": "Qatar | قطر",
      "country_alpha2": "QA",
      "country_alpha3": "QAT",
      "document_type": "REP",
      "has_nfc": false,
      "id": 5168,
      "municipality": null,
      "region_iso": null,
      "region_name": null,
      "tier": null,
      "usecases": [
        "verify"
      ],
      "version": null
    }
  },
  {
    "sourceData": {
      "back_required": true,
      "common_name": null,
      "country": "Qatar | قطر",
      "country_alpha2": "QA",
      "country_alpha3": "QAT",
      "document_type": "REP",
      "has_nfc": false,
      "id": 5931,
      "municipality": null,
      "region_iso": null,
      "region_name": null,
      "tier": null,
      "usecases": [
        "verify"
      ],
      "version": "2"
    }
  },
  {
    "sourceData": {
      "back_required": true,
      "common_name": null,
      "country": "Romania | România",
      "country_alpha2": "RO",
      "country_alpha3": "ROU",
      "document_type": "REP",
      "has_nfc": false,
      "id": 4801,
      "municipality": null,
      "region_iso": null,
      "region_name": null,
      "tier": "tier1",
      "usecases": [
        "verify"
      ],
      "version": "2007"
    }
  },
  {
    "sourceData": {
      "back_required": false,
      "common_name": null,
      "country": "Romania | România",
      "country_alpha2": "RO",
      "country_alpha3": "ROU",
      "document_type": "REP",
      "has_nfc": false,
      "id": 6126,
      "municipality": null,
      "region_iso": null,
      "region_name": null,
      "tier": "tier2",
      "usecases": [
        "verify"
      ],
      "version": "2007-1"
    }
  },
  {
    "sourceData": {
      "back_required": false,
      "common_name": null,
      "country": "Romania | România",
      "country_alpha2": "RO",
      "country_alpha3": "ROU",
      "document_type": "REP",
      "has_nfc": false,
      "id": 8119,
      "municipality": null,
      "region_iso": null,
      "region_name": null,
      "tier": "tier2",
      "usecases": [
        "verify"
      ],
      "version": "2007-2"
    }
  },
  {
    "sourceData": {
      "back_required": false,
      "common_name": null,
      "country": "Romania | România",
      "country_alpha2": "RO",
      "country_alpha3": "ROU",
      "document_type": "REP",
      "has_nfc": false,
      "id": 8120,
      "municipality": null,
      "region_iso": null,
      "region_name": null,
      "tier": "tier2",
      "usecases": [
        "verify"
      ],
      "version": "2007-3"
    }
  },
  {
    "sourceData": {
      "back_required": false,
      "common_name": null,
      "country": "Romania | România",
      "country_alpha2": "RO",
      "country_alpha3": "ROU",
      "document_type": "REP",
      "has_nfc": false,
      "id": 8121,
      "municipality": null,
      "region_iso": null,
      "region_name": null,
      "tier": "tier2",
      "usecases": [
        "verify"
      ],
      "version": "2007-4"
    }
  },
  {
    "sourceData": {
      "back_required": true,
      "common_name": null,
      "country": "Romania | România",
      "country_alpha2": "RO",
      "country_alpha3": "ROU",
      "document_type": "REP",
      "has_nfc": true,
      "id": 10308,
      "municipality": null,
      "region_iso": null,
      "region_name": null,
      "tier": "tier2",
      "usecases": [
        "verify"
      ],
      "version": "2021"
    }
  },
  {
    "sourceData": {
      "back_required": true,
      "common_name": null,
      "country": "Romania | România",
      "country_alpha2": "RO",
      "country_alpha3": "ROU",
      "data_validation_reviewed": true,
      "document_type": "REP",
      "has_nfc": false,
      "id": 10543,
      "municipality": null,
      "region_iso": null,
      "region_name": null,
      "tier": "tier2",
      "usecases": [
        "verify"
      ],
      "version": "2009"
    }
  },
  {
    "sourceData": {
      "back_required": false,
      "common_name": null,
      "country": "Saudi Arabia | السعودية",
      "country_alpha2": "SA",
      "country_alpha3": "SAU",
      "document_type": "REP",
      "has_nfc": false,
      "id": 5172,
      "municipality": null,
      "region_iso": null,
      "region_name": null,
      "tier": null,
      "usecases": [
        "verify"
      ],
      "version": null
    }
  },
  {
    "sourceData": {
      "back_required": false,
      "common_name": null,
      "country": "Saudi Arabia | السعودية",
      "country_alpha2": "SA",
      "country_alpha3": "SAU",
      "document_type": "REP",
      "has_nfc": false,
      "id": 5938,
      "municipality": null,
      "region_iso": null,
      "region_name": null,
      "tier": "tier2",
      "usecases": [
        "verify"
      ],
      "version": "2"
    }
  },
  {
    "sourceData": {
      "back_required": true,
      "common_name": null,
      "country": "Slovakia | Slovensko",
      "country_alpha2": "SK",
      "country_alpha3": "SVK",
      "document_type": "REP",
      "has_nfc": true,
      "id": 3868,
      "municipality": null,
      "region_iso": null,
      "region_name": null,
      "tier": null,
      "usecases": [
        "verify"
      ],
      "version": "2004"
    }
  },
  {
    "sourceData": {
      "back_required": true,
      "common_name": null,
      "country": "Slovakia | Slovensko",
      "country_alpha2": "SK",
      "country_alpha3": "SVK",
      "document_type": "REP",
      "has_nfc": true,
      "id": 6131,
      "municipality": null,
      "region_iso": null,
      "region_name": null,
      "tier": null,
      "usecases": [
        "verify"
      ],
      "version": "2011"
    }
  },
  {
    "sourceData": {
      "back_required": false,
      "common_name": null,
      "country": "Slovakia | Slovensko",
      "country_alpha2": "SK",
      "country_alpha3": "SVK",
      "document_type": "REP",
      "has_nfc": true,
      "id": 8140,
      "municipality": null,
      "region_iso": null,
      "region_name": null,
      "tier": null,
      "usecases": [
        "verify"
      ],
      "version": "2014"
    }
  },
  {
    "sourceData": {
      "back_required": true,
      "common_name": null,
      "country": "Slovakia | Slovensko",
      "country_alpha2": "SK",
      "country_alpha3": "SVK",
      "document_type": "REP",
      "has_nfc": true,
      "id": 9164,
      "municipality": null,
      "region_iso": null,
      "region_name": null,
      "tier": "tier1",
      "usecases": [
        "verify"
      ],
      "version": "2020"
    }
  },
  {
    "sourceData": {
      "back_required": true,
      "common_name": null,
      "country": "Slovenia | Slovenija",
      "country_alpha2": "SI",
      "country_alpha3": "SVN",
      "document_type": "REP",
      "has_nfc": true,
      "id": 3878,
      "municipality": null,
      "region_iso": null,
      "region_name": null,
      "tier": null,
      "usecases": [
        "verify"
      ],
      "version": "2011"
    }
  },
  {
    "sourceData": {
      "back_required": true,
      "common_name": null,
      "country": "Spain | España",
      "country_alpha2": "ES",
      "country_alpha3": "ESP",
      "document_type": "REP",
      "has_nfc": false,
      "id": 3905,
      "municipality": null,
      "region_iso": null,
      "region_name": null,
      "tier": null,
      "usecases": [
        "verify"
      ],
      "version": "2010"
    }
  },
  {
    "sourceData": {
      "back_required": true,
      "common_name": null,
      "country": "Spain | España",
      "country_alpha2": "ES",
      "country_alpha3": "ESP",
      "document_type": "REP",
      "has_nfc": true,
      "id": 4451,
      "municipality": null,
      "region_iso": null,
      "region_name": null,
      "tier": null,
      "usecases": [
        "verify"
      ],
      "version": "2011"
    }
  },
  {
    "sourceData": {
      "back_required": true,
      "common_name": "student",
      "country": "Spain | España",
      "country_alpha2": "ES",
      "country_alpha3": "ESP",
      "document_type": "REP",
      "has_nfc": false,
      "id": 6137,
      "municipality": null,
      "region_iso": null,
      "region_name": null,
      "tier": null,
      "usecases": [
        "verify"
      ],
      "version": "2010"
    }
  },
  {
    "sourceData": {
      "back_required": true,
      "common_name": null,
      "country": "Spain | España",
      "country_alpha2": "ES",
      "country_alpha3": "ESP",
      "document_type": "REP",
      "has_nfc": true,
      "id": 7679,
      "municipality": null,
      "region_iso": null,
      "region_name": null,
      "tier": "tier1",
      "usecases": [
        "verify"
      ],
      "version": "2020"
    }
  },
  {
    "sourceData": {
      "back_required": true,
      "common_name": null,
      "country": "Sweden | Sverige",
      "country_alpha2": "SE",
      "country_alpha3": "SWE",
      "document_type": "REP",
      "has_nfc": true,
      "id": 4878,
      "municipality": null,
      "region_iso": null,
      "region_name": null,
      "tier": null,
      "usecases": [
        "verify"
      ],
      "version": "2011"
    }
  },
  {
    "sourceData": {
      "back_required": true,
      "common_name": null,
      "country": "Sweden | Sverige",
      "country_alpha2": "SE",
      "country_alpha3": "SWE",
      "document_type": "REP",
      "has_nfc": true,
      "id": 4879,
      "municipality": null,
      "region_iso": null,
      "region_name": null,
      "tier": null,
      "usecases": [
        "verify"
      ],
      "version": "2012"
    }
  },
  {
    "sourceData": {
      "back_required": false,
      "common_name": null,
      "country": "Sweden | Sverige",
      "country_alpha2": "SE",
      "country_alpha3": "SWE",
      "document_type": "REP",
      "has_nfc": false,
      "id": 10208,
      "municipality": null,
      "region_iso": null,
      "region_name": null,
      "tier": "tier1",
      "usecases": [
        "verify"
      ],
      "version": "2020"
    }
  },
  {
    "sourceData": {
      "back_required": true,
      "common_name": null,
      "country": "Switzerland | Schweiz",
      "country_alpha2": "CH",
      "country_alpha3": "CHE",
      "document_type": "REP",
      "has_nfc": true,
      "id": 3931,
      "municipality": null,
      "region_iso": null,
      "region_name": null,
      "tier": null,
      "usecases": [
        "verify"
      ],
      "version": "2011"
    }
  },
  {
    "sourceData": {
      "back_required": true,
      "common_name": null,
      "country": "Switzerland | Schweiz",
      "country_alpha2": "CH",
      "country_alpha3": "CHE",
      "document_type": "REP",
      "has_nfc": true,
      "id": 4586,
      "municipality": null,
      "region_iso": null,
      "region_name": null,
      "tier": null,
      "usecases": [
        "verify"
      ],
      "version": "2008"
    }
  },
  {
    "sourceData": {
      "back_required": true,
      "common_name": null,
      "country": "Switzerland | Schweiz",
      "country_alpha2": "CH",
      "country_alpha3": "CHE",
      "document_type": "REP",
      "has_nfc": false,
      "id": 8240,
      "municipality": null,
      "region_iso": null,
      "region_name": null,
      "tier": "tier1",
      "usecases": [
        "verify"
      ],
      "version": "2019"
    }
  },
  {
    "sourceData": {
      "back_required": true,
      "common_name": null,
      "country": "Switzerland | Schweiz",
      "country_alpha2": "CH",
      "country_alpha3": "CHE",
      "document_type": "REP",
      "has_nfc": true,
      "id": 9165,
      "municipality": null,
      "region_iso": null,
      "region_name": null,
      "tier": "tier1",
      "usecases": [
        "verify"
      ],
      "version": "2020"
    }
  },
  {
    "sourceData": {
      "back_required": false,
      "common_name": null,
      "country": "Switzerland | Schweiz",
      "country_alpha2": "CH",
      "country_alpha3": "CHE",
      "document_type": "REP",
      "has_nfc": false,
      "id": 10238,
      "municipality": null,
      "region_iso": null,
      "region_name": null,
      "tier": "tier3",
      "usecases": [
        "verify"
      ],
      "version": null
    }
  },
  {
    "sourceData": {
      "back_required": true,
      "common_name": null,
      "country": "Taiwan, Province of China | 中華民國",
      "country_alpha2": "TW",
      "country_alpha3": "TWN",
      "document_type": "REP",
      "has_nfc": false,
      "id": 5178,
      "municipality": null,
      "region_iso": null,
      "region_name": null,
      "tier": null,
      "usecases": [
        "verify"
      ],
      "version": "1"
    }
  },
  {
    "sourceData": {
      "back_required": true,
      "common_name": null,
      "country": "Taiwan, Province of China | 中華民國",
      "country_alpha2": "TW",
      "country_alpha3": "TWN",
      "document_type": "REP",
      "has_nfc": false,
      "id": 5951,
      "municipality": null,
      "region_iso": null,
      "region_name": null,
      "tier": null,
      "usecases": [
        "verify"
      ],
      "version": "2"
    }
  },
  {
    "sourceData": {
      "back_required": false,
      "common_name": null,
      "country": "Tanzania, United Republic of",
      "country_alpha2": "TZ",
      "country_alpha3": "TZA",
      "document_type": "REP",
      "has_nfc": false,
      "id": 5436,
      "municipality": null,
      "region_iso": null,
      "region_name": null,
      "tier": null,
      "usecases": [
        "verify"
      ],
      "version": null
    }
  },
  {
    "sourceData": {
      "back_required": true,
      "common_name": null,
      "country": "Timor-Leste | Timor Lorosa'e",
      "country_alpha2": "TL",
      "country_alpha3": "TLS",
      "document_type": "REP",
      "has_nfc": false,
      "id": 9877,
      "municipality": null,
      "region_iso": null,
      "region_name": null,
      "tier": "tier3",
      "usecases": [
        "verify"
      ],
      "version": null
    }
  },
  {
    "sourceData": {
      "back_required": true,
      "common_name": null,
      "country": "Turkey | Türkiye",
      "country_alpha2": "TR",
      "country_alpha3": "TUR",
      "document_type": "REP",
      "has_nfc": false,
      "id": 5139,
      "municipality": null,
      "region_iso": null,
      "region_name": null,
      "tier": null,
      "usecases": [
        "verify"
      ],
      "version": null
    }
  },
  {
    "sourceData": {
      "back_required": true,
      "common_name": null,
      "country": "Turkey | Türkiye",
      "country_alpha2": "TR",
      "country_alpha3": "TUR",
      "document_type": "REP",
      "has_nfc": false,
      "id": 6136,
      "municipality": null,
      "region_iso": null,
      "region_name": null,
      "tier": null,
      "usecases": [
        "verify"
      ],
      "version": "2"
    }
  },
  {
    "sourceData": {
      "back_required": false,
      "common_name": null,
      "country": "Ukraine | Ukraїna",
      "country_alpha2": "UA",
      "country_alpha3": "UKR",
      "document_type": "REP",
      "has_nfc": false,
      "id": 10097,
      "municipality": null,
      "region_iso": null,
      "region_name": null,
      "tier": "tier1",
      "usecases": [
        "verify"
      ],
      "version": "2018"
    }
  },
  {
    "sourceData": {
      "back_required": true,
      "common_name": null,
      "country": "Ukraine | Ukraїna",
      "country_alpha2": "UA",
      "country_alpha3": "UKR",
      "document_type": "REP",
      "has_nfc": true,
      "id": 10341,
      "municipality": null,
      "region_iso": null,
      "region_name": null,
      "tier": "tier1",
      "usecases": [
        "verify"
      ],
      "version": "2018"
    }
  },
  {
    "sourceData": {
      "back_required": false,
      "common_name": null,
      "country": "Ukraine | Ukraїna",
      "country_alpha2": "UA",
      "country_alpha3": "UKR",
      "document_type": "REP",
      "has_nfc": false,
      "id": 9890,
      "municipality": null,
      "region_iso": null,
      "region_name": null,
      "tier": "tier2",
      "usecases": [
        "verify"
      ],
      "version": null
    }
  },
  {
    "sourceData": {
      "back_required": false,
      "common_name": null,
      "country": "Ukraine | Ukraїna",
      "country_alpha2": "UA",
      "country_alpha3": "UKR",
      "document_type": "REP",
      "has_nfc": false,
      "id": 10559,
      "municipality": null,
      "region_iso": null,
      "region_name": null,
      "tier": "tier2",
      "usecases": [
        "verify"
      ],
      "version": "2"
    }
  },
  {
    "sourceData": {
      "back_required": true,
      "common_name": null,
      "country": "United Arab Emirates | الإمارات العربية المتحدة",
      "country_alpha2": "AE",
      "country_alpha3": "ARE",
      "document_type": "REP",
      "has_nfc": false,
      "id": 5181,
      "municipality": null,
      "region_iso": null,
      "region_name": null,
      "tier": null,
      "usecases": [
        "verify"
      ],
      "version": "1"
    }
  },
  {
    "sourceData": {
      "back_required": true,
      "common_name": null,
      "country": "United Arab Emirates | الإمارات العربية المتحدة",
      "country_alpha2": "AE",
      "country_alpha3": "ARE",
      "document_type": "REP",
      "has_nfc": true,
      "id": 10225,
      "municipality": null,
      "region_iso": null,
      "region_name": null,
      "tier": "tier1",
      "usecases": [
        "verify"
      ],
      "version": "2"
    }
  },
  {
    "sourceData": {
      "back_required": true,
      "common_name": null,
      "country": "United Arab Emirates | الإمارات العربية المتحدة",
      "country_alpha2": "AE",
      "country_alpha3": "ARE",
      "document_type": "REP",
      "has_nfc": true,
      "id": 10322,
      "municipality": null,
      "region_iso": null,
      "region_name": null,
      "tier": "tier1",
      "usecases": [
        "verify"
      ],
      "version": "2021"
    }
  },
  {
    "sourceData": {
      "back_required": true,
      "common_name": null,
      "country": "United Arab Emirates | الإمارات العربية المتحدة",
      "country_alpha2": "AE",
      "country_alpha3": "ARE",
      "document_type": "REP",
      "has_nfc": true,
      "id": 10323,
      "municipality": null,
      "region_iso": null,
      "region_name": null,
      "tier": "tier1",
      "usecases": [
        "verify"
      ],
      "version": "2021"
    }
  },
  {
    "sourceData": {
      "back_required": true,
      "common_name": null,
      "country": "United Arab Emirates | الإمارات العربية المتحدة",
      "country_alpha2": "AE",
      "country_alpha3": "ARE",
      "document_type": "REP",
      "has_nfc": false,
      "id": 10546,
      "municipality": null,
      "region_iso": null,
      "region_name": null,
      "tier": "tier1",
      "usecases": [
        "verify"
      ],
      "version": "2021 1"
    }
  },
  {
    "sourceData": {
      "back_required": false,
      "common_name": null,
      "country": "United Kingdom of Great Britain and Northern Ireland",
      "country_alpha2": "GB",
      "country_alpha3": "GBR",
      "document_type": "REP",
      "has_nfc": false,
      "id": 4474,
      "municipality": null,
      "region_iso": null,
      "region_name": null,
      "tier": "tier2",
      "usecases": [
        "verify",
        "right_to_work"
      ],
      "version": "2010"
    }
  },
  {
    "sourceData": {
      "back_required": false,
      "common_name": null,
      "country": "United Kingdom of Great Britain and Northern Ireland",
      "country_alpha2": "GB",
      "country_alpha3": "GBR",
      "document_type": "REP",
      "has_nfc": false,
      "id": 4475,
      "municipality": null,
      "region_iso": null,
      "region_name": null,
      "tier": "tier2",
      "usecases": [
        "verify",
        "right_to_work"
      ],
      "version": "2012"
    }
  },
  {
    "sourceData": {
      "back_required": true,
      "common_name": null,
      "country": "United Kingdom of Great Britain and Northern Ireland",
      "country_alpha2": "GB",
      "country_alpha3": "GBR",
      "document_type": "REP",
      "has_nfc": true,
      "id": 6296,
      "municipality": null,
      "region_iso": null,
      "region_name": null,
      "tier": null,
      "usecases": [
        "verify"
      ],
      "version": "2010-1"
    }
  },
  {
    "sourceData": {
      "back_required": true,
      "common_name": null,
      "country": "United Kingdom of Great Britain and Northern Ireland",
      "country_alpha2": "GB",
      "country_alpha3": "GBR",
      "document_type": "REP",
      "has_nfc": false,
      "id": 10023,
      "municipality": null,
      "region_iso": "UKM",
      "region_name": "United Kingdom",
      "tier": "tier1",
      "usecases": [
        "verify"
      ],
      "version": "2010 2"
    }
  },
  {
    "sourceData": {
      "back_required": true,
      "common_name": null,
      "country": "United Kingdom of Great Britain and Northern Ireland",
      "country_alpha2": "GB",
      "country_alpha3": "GBR",
      "document_type": "REP",
      "has_nfc": false,
      "id": 10038,
      "municipality": null,
      "region_iso": null,
      "region_name": null,
      "tier": null,
      "usecases": [
        "verify"
      ],
      "version": "2021 1"
    }
  },
  {
    "sourceData": {
      "back_required": true,
      "common_name": null,
      "country": "United Kingdom of Great Britain and Northern Ireland",
      "country_alpha2": "GB",
      "country_alpha3": "GBR",
      "document_type": "REP",
      "has_nfc": false,
      "id": 10048,
      "municipality": null,
      "region_iso": null,
      "region_name": null,
      "tier": null,
      "usecases": [
        "verify"
      ],
      "version": "2021 2"
    }
  },
  {
    "sourceData": {
      "back_required": true,
      "common_name": null,
      "country": "United Kingdom of Great Britain and Northern Ireland",
      "country_alpha2": "GB",
      "country_alpha3": "GBR",
      "document_type": "REP",
      "has_nfc": true,
      "id": 6293,
      "municipality": null,
      "region_iso": null,
      "region_name": null,
      "tier": null,
      "usecases": [
        "verify"
      ],
      "version": "2015"
    }
  },
  {
    "sourceData": {
      "back_required": false,
      "common_name": "Green Card",
      "country": "United States of America",
      "country_alpha2": "US",
      "country_alpha3": "USA",
      "document_type": "REP",
      "has_nfc": false,
      "id": 5108,
      "municipality": null,
      "region_iso": null,
      "region_name": null,
      "tier": null,
      "usecases": [
        "verify"
      ],
      "version": "2010"
    }
  },
  {
    "sourceData": {
      "back_required": false,
      "common_name": null,
      "country": "United States of America",
      "country_alpha2": "US",
      "country_alpha3": "USA",
      "document_type": "REP",
      "has_nfc": false,
      "id": 5406,
      "municipality": null,
      "region_iso": null,
      "region_name": null,
      "tier": null,
      "usecases": [
        "verify"
      ],
      "version": "2008"
    }
  },
  {
    "sourceData": {
      "back_required": true,
      "common_name": "Green Card",
      "country": "United States of America",
      "country_alpha2": "US",
      "country_alpha3": "USA",
      "document_type": "REP",
      "has_nfc": false,
      "id": 6826,
      "municipality": null,
      "region_iso": null,
      "region_name": null,
      "tier": null,
      "usecases": [
        "verify"
      ],
      "version": "2017"
    }
  },
  {
    "sourceData": {
      "back_required": false,
      "common_name": null,
      "country": "Viet Nam | Việt Nam",
      "country_alpha2": "VN",
      "country_alpha3": "VNM",
      "document_type": "REP",
      "has_nfc": false,
      "id": 9979,
      "municipality": null,
      "region_iso": null,
      "region_name": null,
      "tier": null,
      "usecases": [
        "verify"
      ],
      "version": null
    }
  }
]